doid/__init__.py
doid/container.py
doid/filter.py
doid/tests/__init__.py
doid/tests/test_interfaces.py
doid-0.0.1.dist-info/METADATA
doid-0.0.1.dist-info/RECORD
doid-0.0.1.dist-info/WHEEL
doid-0.0.1.dist-info/top_level.txt
