Metadata-Version: 2.1
Name: doid
Version: 0.0.1
Summary: Generic container with complex filter/sorting
Home-page: https://github.com/scardine/doid
Author: Paulo Scardine
Author-email: paulo@xtend.com.br
License: UNKNOWN
Platform: UNKNOWN
Classifier: Programming Language :: Python :: 3
Classifier: License :: OSI Approved :: MIT License
Classifier: Operating System :: OS Independent
